LICENSE
MANIFEST.in
README.rst
setup.py
geokey_import/__init__.py
geokey_import/exceptions.py
geokey_import/models.py
geokey_import/urls.py
geokey_import/views.py
geokey_import.egg-info/PKG-INFO
geokey_import.egg-info/SOURCES.txt
geokey_import.egg-info/dependency_links.txt
geokey_import.egg-info/top_level.txt
geokey_import/migrations/0001_initial.py
geokey_import/migrations/0002_dataimport_imported.py
geokey_import/migrations/0003_dataimport_geom_field.py
geokey_import/migrations/__init__.py
geokey_import/templatetags/__init__.py
geokey_import/templatetags/import_tags.py
geokey_import/utils/__init__.py
geokey_import/utils/category.py
geokey_import/utils/csv_parser.py
travis/__init__.py
travis/manage.py
travis/settings/__init__.py
travis/settings/settings.py
travis/settings/urls.py
travis/settings/wsgi.py