Metadata-Version: 1.1
Name: geokey-import
Version: 0.1.0
Summary: Impot data to GeoKey from CSV
Home-page: https://github.com/ExCiteS/geokey-import
Author: ExCiteS
Author-email: excitesucl@gmail.com
License: MIT
Download-URL: https://github.com/ExCiteS/geokey-import/tarball/0.1.0
Platform: UNKNOWN
